pypsg/__init__.py
pypsg/docker.py
pypsg/exceptions.py
pypsg/request.py
pypsg/settings.py
pypsg/units.py
pypsg/cfg/__init__.py
pypsg/cfg/base.py
pypsg/cfg/config.py
pypsg/cfg/models.py
pypsg/globes/__init__.py
pypsg/globes/decoder.py
pypsg/globes/globes.py
pypsg/globes/molec.json
pypsg/globes/structure.py
pypsg/globes/exocam/__init__.py
pypsg/globes/exocam/exocam.py
pypsg/globes/exoplasim/__init__.py
pypsg/globes/exoplasim/exoplasim.py
pypsg/globes/waccm/__init__.py
pypsg/globes/waccm/waccm.py
pypsg/lyr/__init__.py
pypsg/lyr/lyr.py
pypsg/rad/__init__.py
pypsg/rad/rad.py
pypsg/trn/__init__.py
pypsg/trn/trn.py
pypsg-0.3.2.dist-info/LICENSE
pypsg-0.3.2.dist-info/METADATA
pypsg-0.3.2.dist-info/WHEEL
pypsg-0.3.2.dist-info/top_level.txt
pypsg-0.3.2.dist-info/RECORD
